Workbook

Sheet Feasibility Study
A1: Feasibility Study – E-commerce Product Review & Rating System
A2: Course Project: System Analysis | Menoufia University | ENG: Eman Abdelroof
A4: Type | B4: Current Situation / Considerations | C4: Proposed Solution / Benefits | D4: Feasibility Result
A5: Technical | B5: No verified customer feedback on product pages; no automated way to filter spam/fake reviews; no analytics to spot low-quality products. | C5: React.js/HTML5/CSS3 front end; SQL Server or PostgreSQL relational database (users, products, orders, reviews); Python (Pandas, NLTK/TextBlob) for spam filtering and sentiment analysis; Tableau dashboards connected to the database; cloud-hosted. | D5: ✅ Technically feasible
A6: Operational | B6: Customers doubt product quality; high cancellations and returns; managers cannot quickly identify low-quality products; support staff would be overloaded if all reviews were checked manually. | C6: Verified buyers only (linked to order database); automated moderation so support reviews flagged content only; Tableau dashboards for top/low-rated products; fast decisions such as removing defective inventory. | D6: ✅ Operationally feasible
A7: Economic | B7: Cost of development, Tableau licenses, cloud hosting/storage for photos and videos, training, and maintenance. | C7: Built as an add-on module (no rebuild of the store); expected 15–20% increase in completed orders; fewer returns; low maintenance through automated Python scripts. See the Cost-Benefit Analysis sheet. | D7: ✅ Cost-effective
A8: Legal | B8: Handling user accounts, order history and user-uploaded photos/videos; risk of defamatory or false reviews damaging store credibility. | C8: Privacy and security policy for user data (compliance with the applicable data-protection law, e.g. Egypt's Personal Data Protection Law); terms of use covering user-generated content and media rights; verified-buyer rule and report/removal process. | D8: ✅ Legally feasible
A9: Schedule | B9: Deadline: before 1 January. Integration must not slow down website load speed. | C9: Phased plan: requirements → design → database & back end → front end & moderation → Tableau dashboards → testing → deployment, with a lean module scope to meet the deadline. | D9: ✅ Achievable timeline (if scope stays focused)

Sheet Cost-Benefit Analysis
A1: Cost–Benefit Analysis – E-commerce Product Review & Rating System
A2: All amounts in USD. Cost figures are estimates (blue); benefit values are calculated from the Assumptions sheet.
A4: Category | B4: Description | C4: Estimated Cost – Low | D4: Estimated Cost – High | E4: Benefits | F4: Est. Value per Year – Low | G4: Est. Value per Year – High
A5: Software Development | B5: In-house development of the review module: React front end, SQL database, review/rating/media upload, Python moderation scripts | C5: 3000 | D5: 6000 | E5: Verified-buyer reviews, ratings and photos build trust and lift completed orders. | F5: =Assumptions!$B$5*Assumptions!$B$6*Assumptions!$B$8 -> 6000 | G5: =Assumptions!$B$5*Assumptions!$B$7*Assumptions!$B$8 -> 8000
A6: Analytics (Tableau) | B6: Tableau licences and dashboards connected to the SQL database | C6: 900 | D6: 1800 | E6: Managers spot top/low-rated products quickly and remove defective stock. | F6: =Assumptions!$B$14 -> 1000 | G6: =Assumptions!$B$15 -> 2000
A7: Cloud Hosting & Storage | B7: Cloud servers, database and storage for customer photos/videos | C7: 600 | D7: 1500 | E7: Scalable, runs separately so site load speed is not affected. | F7: Intangible | G7: Intangible
A8: Training | B8: Short training for store managers and support staff on dashboards and flagged-content review | C8: 300 | D8: 800 | E8: Smooth adoption and efficient use of the system. | F8: Intangible | G8: Intangible
A9: Maintenance | B9: Updates, bug fixes, monitoring of spam/sentiment scripts | C9: 800 | D9: 1500 | E9: Reliable and secure system with low computational overhead. | F9: Intangible | G9: Intangible
A10: Moderation | B10: Support team time to review only the content flagged by the filters | C10: 500 | D10: 1000 | E10: Automated NLP filters replace manual checking of every review. | F10: =Assumptions!$B$12 -> 1500 | G10: =Assumptions!$B$13 -> 2500
A11: Returns & Cancellations | B11: Current cost of returned and cancelled orders | C11: – | D11: – | E11: Accurate ratings and buyer photos set correct expectations. | F11: =Assumptions!$B$9*Assumptions!$B$10 -> 2000 | G11: =Assumptions!$B$9*Assumptions!$B$11 -> 3000
A12: Customer Trust & Brand Loyalty | B12: Doubt about quality and fake reviews damage credibility | C12: – | D12: – | E12: Genuine verified feedback improves trust, engagement and repeat purchases. | F12: Intangible but high value | G12: Intangible but high value
A13: TOTAL | C13: =SUM(C5:C12) -> 6100 | D13: =SUM(D5:D12) -> 12600 | F13: =SUM(F5:F12) -> 10500 | G13: =SUM(G5:G12) -> 15500
A15: Summary
A16: Item | C16: Low estimate | D16: High estimate
A17: Total Estimated Costs (first year) | C17: =C13 -> 6100 | D17: =D13 -> 12600
A18: Total Estimated Annual Benefits / Savings | C18: =F13 -> 10500 | D18: =G13 -> 15500
A19: Net Annual Benefit | C19: =C18-C17 -> 4400 | D19: =D18-D17 -> 2900
A20: Payback Period (months) | C20: =IF(C18>0,C17/C18*12,"n/a") -> 6.9714286 | D20: =IF(D18>0,D17/D18*12,"n/a") -> 9.7548387
A22: =IF(MAX(C20,D20)<=12,"Conclusion: The Review & Rating System is economically feasible, with payback within 1 year and clear long-term value (trust, loyalty, quality control).","Conclusion: Payback exceeds 1 year in at least one scenario – review costs and assumptions.") -> Conclusion: The Review & Rating System is economically feasible, with payback within 1 year and clear long-term value (trust, loyalty, quality control).

Sheet Assumptions
A1: Assumptions (edit the yellow cells)
A2: Blue = input. Yellow = replace with your real store figures. Everything in the Cost-Benefit sheet recalculates from here.
A4: Assumption | B4: Value | C4: Source / Note
A5: Annual online sales (USD) | B5: 200000 | C5: PLACEHOLDER – replace with the store's real annual sales.
A6: Order conversion uplift – low | B6: 0.15 | C6: From project brief: 15–20% increase in completed checkout orders.
A7: Order conversion uplift – high | B7: 0.2 | C7: From project brief.
A8: Average profit margin on sales | B8: 0.2 | C8: Assumption – replace with real margin.
A9: Annual cost of returns & cancellations (USD) | B9: 10000 | C9: PLACEHOLDER – replace with the store's real figure.
A10: Reduction in returns – low | B10: 0.2 | C10: Assumption: accurate ratings and buyer photos set better expectations.
A11: Reduction in returns – high | B11: 0.3 | C11: Assumption.
A12: Moderation labour saved per year – low (USD) | B12: 1500 | C12: Assumption: automated filtering instead of manual review of all reviews.
A13: Moderation labour saved per year – high (USD) | B13: 2500 | C13: Assumption.
A14: Quality-control savings per year – low (USD) | B14: 1000 | C14: Assumption: faster removal of defective/low-rated stock.
A15: Quality-control savings per year – high (USD) | B15: 2000 | C15: Assumption.
